app/__init__.py
app/main.py
app/models.py
app/routes/__init__.py
app/routes/assistants.py
app/routes/messages.py
app/routes/runs.py
app/routes/threads.py
app/services/__init__.py
app/services/connector.py
app/services/database.py
app/services/llm_service.py
app/services/open_interpreter_service.py
app/services/serverless_service.py
tests/__init__.py
tests/test_assistants.py
tests/test_messages.py
tests/test_runs.py
tests/test_threads.py
pygentic-0.2.3.dist-info/LICENSE
pygentic-0.2.3.dist-info/METADATA
pygentic-0.2.3.dist-info/WHEEL
pygentic-0.2.3.dist-info/entry_points.txt
pygentic-0.2.3.dist-info/top_level.txt
pygentic-0.2.3.dist-info/RECORD
