Metadata-Version: 2.1
Name: pygentic
Version: 0.2.3
Summary: An innovative system designed to enhance the capabilities of AI assistants by providing a flexible and standardized API.
Home-page: https://github.com/ruvnet/pygentic
Author: Your Name
Author-email: your-email@example.com
License: Apache License 2.0
Classifier: Development Status :: 3 - Alpha
Classifier: Intended Audience :: Developers
Classifier: Topic :: Software Development :: Libraries :: Application Frameworks
Classifier: License :: OSI Approved :: Apache Software License
Classifier: Programming Language :: Python :: 3.7
Classifier: Programming Language :: Python :: 3.8
Classifier: Programming Language :: Python :: 3.9
Classifier: Programming Language :: Python :: 3.10
License-File: LICENSE
Requires-Dist: fastapi
Requires-Dist: pydantic
Requires-Dist: httpx
Requires-Dist: uvicorn
Requires-Dist: liteLLM
Requires-Dist: pydbantic
Requires-Dist: databases[sqlite]
Requires-Dist: pytest
Requires-Dist: pytest-asyncio
Requires-Dist: sqlalchemy
